Metadata-Version: 2.4
Name: aiguard-sdk
Version: 0.1.0
Summary: AIGuard SDK for monitoring and logging AI model invocations
Author: AIGuard
License: MIT
Project-URL: Homepage, https://github.com/yourusername/aiguard
Project-URL: Documentation, https://github.com/yourusername/aiguard#readme
Project-URL: Repository, https://github.com/yourusername/aiguard
Keywords: ai,monitoring,logging,openai,llm
Classifier: Development Status :: 3 - Alpha
Classifier: Intended Audience :: Developers
Classifier: License :: OSI Approved :: MIT License
Classifier: Programming Language :: Python :: 3
Classifier: Programming Language :: Python :: 3.8
Classifier: Programming Language :: Python :: 3.9
Classifier: Programming Language :: Python :: 3.10
Classifier: Programming Language :: Python :: 3.11
Classifier: Programming Language :: Python :: 3.12
Requires-Python: >=3.8
Requires-Dist: requests>=2.25.0
Provides-Extra: dev
Requires-Dist: pytest>=7.0.0; extra == "dev"
Requires-Dist: pytest-cov>=4.0.0; extra == "dev"
